calculadora_do_fillipe/__init__.py
calculadora_do_fillipe/calculator.py
calculadora_do_fillipe-0.2.0.dist-info/WHEEL
calculadora_do_fillipe-0.2.0.dist-info/METADATA
calculadora_do_fillipe-0.2.0.dist-info/RECORD
