Metadata-Version: 2.1
Name: calculadora-do-fillipe
Version: 0.2.0
Summary: Nova biblioteca bonita em time!
Author: Mariana Pinheiro
Author-email: mariana.pinheiro@loggi.com
Requires-Python: >=3.7,<4.0
Classifier: Programming Language :: Python :: 3
Classifier: Programming Language :: Python :: 3.10
Classifier: Programming Language :: Python :: 3.7
Classifier: Programming Language :: Python :: 3.8
Classifier: Programming Language :: Python :: 3.9
